{
  "pr_number": 1325,
  "title": "Record Submission: Poly5 Softcap + Z-Loss + YaRN + Zstd-22 + Stride-16 (on PR #549 stack)",
  "author": "monisha-max",
  "status": "open",
  "val_bpb": 1.3868,
  "architecture": "Transformer",
  "quantization": null,
  "optimizer": "Parallel Muon",
  "training_techniques": [
    {
      "category": "regularization",
      "data": {
        "method": "logit softcap",
        "parameters": {
          "type": "poly5"
        }
      }
    },
    {
      "category": "regularization",
      "data": {
        "method": "logit softcap",
        "parameters": {
          "type": "z-loss",
          "weight": 0.0001
        }
      }
    },
    {
      "category": "architecture_modification",
      "data": {
        "component": "RoPE",
        "description": "YaRN positional encoding for improved frequency interpolation",
        "parameters": {
          "max_len": 2048
        }
      }
    },
    {
      "category": "compression",
      "data": {
        "method": "zstd",
        "level": 22
      }
    },
    {
      "category": "evaluation_technique",
      "data": {
        "method": "sliding window eval",
        "parameters": {
          "stride": 16
        }
      }
    },
    {
      "category": "other",
      "data": {
        "description": "FA3/FA2/SDPA fallback for broader GPU compatibility",
        "parameters": null
      }
    },
    {
      "category": "regularization",
      "data": {
        "method": "adaptive focal loss",
        "parameters": {
          "gamma": 1.0
        }
      }
    },
    {
      "category": "quantization",
      "data": {
        "method": "mixed int6/int4",
        "bits": 6,
        "scope": "weights"
      }
    },
    {
      "category": "other",
      "data": {
        "description": "Residual vector quantization using int6 base plus int4 residual",
        "parameters": null
      }
    },
    {
      "category": "other",
      "data": {
        "description": "Progressive depth warmup with staged layer freezing/unfreezing during training",
        "parameters": {
          "stages": 3
        }
      }
    },
    {
      "category": "test_time_training",
      "data": {
        "method": "score-first TTT",
        "parameters": {
          "epochs": 3
        }
      }
    },
    {
      "category": "architecture_modification",
      "data": {
        "component": "BigramHash",
        "description": "Bigram vocabulary embedding component",
        "parameters": {
          "size": 1536
        }
      }
    },
    {
      "category": "architecture_modification",
      "data": {
        "component": "SmearGate",
        "description": "SmearGate embedding/attention component",
        "parameters": null
      }
    },
    {
      "category": "architecture_modification",
      "data": {
        "component": "U-Net skip connections",
        "description": "U-Net style encoder-decoder skip connections with learned skip weights",
        "parameters": {
          "encoders": 5,
          "decoders": 6
        }
      }
    },
    {
      "category": "architecture_modification",
      "data": {
        "component": "LeakyReLU",
        "description": "LeakyReLU squared MLP activation",
        "parameters": {
          "slope": 0.5
        }
      }
    },
    {
      "category": "architecture_modification",
      "data": {
        "component": "XSA",
        "description": "Cross/self attention variant used in the last 4 layers",
        "parameters": {
          "last_layers": 4
        }
      }
    },
    {
      "category": "architecture_modification",
      "data": {
        "component": "VE128",
        "description": "Value embeddings at later layers",
        "parameters": {
          "layers": [
            9,
            10
          ]
        }
      }
    },
    {
      "category": "weight_averaging",
      "data": {
        "method": "EMA + SWA",
        "parameters": {
          "ema_decay": 0.997
        }
      }
    },
    {
      "category": "optimizer_technique",
      "data": {
        "method": "AdamW",
        "weight_decay": 0.04,
        "momentum": null,
        "other_params": null
      }
    },
    {
      "category": "lr_schedule",
      "data": {
        "method": "warmdown",
        "parameters": {
          "warmdown_steps": 3500
        }
      }
    },
    {
      "category": "sequence_length",
      "data": {
        "train_length": null,
        "eval_length": 2048
      }
    }
  ],
  "compression": "zstd-22",
  "novel_contributions": [
    "Adaptive focal cross-entropy loss",
    "Residual vector quantization",
    "Progressive depth warmup",
    "Poly5 softcap",
    "Z-loss regularization",
    "YaRN positional encoding",
    "zstd-22 compression",
    "Sliding eval stride=16",
    "FA3/FA2/SDPA fallback"
  ],
  "artifact_size": "7.0 MB",
  "prompt_version": "v2",
  "is_record": false
}