{
  "pr_number": 1660,
  "title": "Record: SP8192 + 3-Layer Recurrence + Hard Onset \u2014 val_bpb 1.0858",
  "author": "pablinga19",
  "status": "closed",
  "val_bpb": 1.0858,
  "architecture": "Transformer",
  "quantization": "GPTQ int6",
  "optimizer": "Muon",
  "training_techniques": [
    {
      "category": "architecture_modification",
      "data": {
        "component": "depth recurrence",
        "description": "3-layer recurrence with layers 3, 4, 5 repeated as virtual layers and activated via hard gate",
        "parameters": {
          "layers": [
            3,
            4,
            5
          ],
          "onset_step": 3000
        }
      }
    },
    {
      "category": "weight_averaging",
      "data": {
        "method": "EMA",
        "parameters": {
          "decay": 0.9965
        }
      }
    },
    {
      "category": "quantization",
      "data": {
        "method": "GPTQ",
        "bits": 6,
        "scope": "all"
      }
    },
    {
      "category": "compression",
      "data": {
        "method": "brotli",
        "level": null
      }
    },
    {
      "category": "evaluation_technique",
      "data": {
        "method": "sliding window eval",
        "parameters": null
      }
    },
    {
      "category": "optimizer_technique",
      "data": {
        "method": "Muon",
        "weight_decay": 0.095,
        "momentum": 0.99,
        "other_params": null
      }
    },
    {
      "category": "regularization",
      "data": {
        "method": "logit softcap",
        "parameters": {
          "value": 30.0
        }
      }
    },
    {
      "category": "sequence_length",
      "data": {
        "train_length": 2048,
        "eval_length": null
      }
    },
    {
      "category": "lr_schedule",
      "data": {
        "method": "warmdown",
        "parameters": {
          "warmup_steps": 20,
          "warmdown_frac": 0.72
        }
      }
    },
    {
      "category": "architecture_modification",
      "data": {
        "component": "LeakyReLU",
        "description": "LeakyReLU squared activation",
        "parameters": {
          "slope": 0.5
        }
      }
    }
  ],
  "compression": "brotli",
  "novel_contributions": [
    "3-layer recurrence over layers 3, 4, and 5 with hard onset at step 3000",
    "Elimination of validation pauses to reclaim wallclock for additional training steps",
    "GPTQ int6 quantization with brotli compression under the 16MB artifact limit",
    "No test-time training",
    "EMA with decay 0.9965 and Muon optimizer configuration"
  ],
  "artifact_size": "15.86 MB",
  "prompt_version": "v2",
  "is_record": false
}