{
  "pr_number": 736,
  "title": "Submit 9L 2xMLP optimized parameter run with val_bpb 1.2168",
  "author": "Git-Aarya",
  "status": "open",
  "is_record": false,
  "val_bpb": 1.2168,
  "architecture": "Transformer",
  "quantization": null,
  "optimizer": null,
  "training_techniques": [
    {
      "category": "architecture_modification",
      "data": {
        "component": "MLP3x",
        "description": "Uses a 9-layer model with 2x MLP multiplier as part of the architecture tuning.",
        "parameters": {
          "layers": 9,
          "mlp_multiplier": 2
        }
      }
    },
    {
      "category": "sequence_length",
      "data": {
        "train_length": 2048,
        "eval_length": null
      }
    },
    {
      "category": "lr_schedule",
      "data": {
        "method": "warmdown",
        "parameters": {
          "warmdown_steps": 3600
        }
      }
    }
  ],
  "compression": null,
  "novel_contributions": [
    "Maintained a 9-layer, 2x MLP architecture",
    "Increased training sequence length to 2048",
    "Tuned matrix learning rate to 0.055",
    "Extended warmdown iterations to 3600",
    "Achieved a reported validation BPB of 1.2168 within a 15.8 MB artifact size"
  ],
  "artifact_size": "15.8 MB"
}