{
  "number": 1545,
  "title": "Record: GDN-Hybrid (Gated DeltaNet + SWA) \u2014 val_bpb 1.028308 (3-seed cold-cache mean)",
  "author": "Abhishek8108",
  "body": "## Summary\n\n**val_bpb = 1.028308** (3-seed cold-cache mean) | 14.48\u201314.70 MB | 8\u00d7H100 SXM\n\nFirst non-transformer architecture in the 10-min record track. Beats merged SOTA (PR #1493, 1.0810) by **5.27 centiBPB**. No TTT. Fixed predictor.\n\n## Architecture\n\nGDN-Hybrid replaces the transformer backbone with **Gated DeltaNet** (delta-rule linear recurrence) + **Sliding Window Attention**:\n\n```\n[GDN\u00d75] \u2192 [SWA] \u2192 [GDN\u00d75] \u2192 [SWA_shared]\n```\n\n- 33,862,953 params, 512-dim, SP1024 tokenizer\n- GDN: `fla.layers.GatedDeltaNet`, head_dim=64, use_short_conv=True\n- SWA: window=512, 8 heads / 4 KV heads, weight-shared across both layers\n- QK-Gain 5.0, BigramHash(3072\u00d7112) + trigram embeddings, logit softcap 30.0\n- Quantization: full-Hessian int6 GPTQ + zstd-22\n\n## 3-Seed Results (cold-cache, fresh pods)\n\n| Seed | Steps | EMA BPB  | **Quantized BPB** | Artifact (bytes) |\n|------|-------|----------|-------------------|-----------------|\n| 42   | 1857  | 1.017970 | **1.027163**      | 15,188,240      |\n| 1337 | 1858  | 1.018624 | **1.027614**      | 15,417,768      |\n| 2024 | 1858  | 1.020559 | **1.030148**      | 15,314,099      |\n| **Mean** | \u2014 | **1.019051** | **1.028308** | \u2014 |\n| **Std**  | \u2014 | 0.001356 | 0.001610 | \u2014 |\n\nAll three seeds run on separate fresh pods. Cold-start signature confirmed (step 1 at ~105s, Triton JIT overhead). t-stat = 56.7 vs SOTA threshold, p \u226a 0.01.\n\n## Reproduction\n\n```bash\npip install flash-linear-attention zstandard sentencepiece\npython3 data/cached_challenge_fineweb.py --variant sp1024\n\nSEED=42 ARCH_MODE=D MAX_WALLCLOCK_SECONDS=590 ITERATIONS=9999 \\\n  TRAIN_SEQ_LEN=2048 TRAIN_BATCH_TOKENS=786432 \\\n  QK_GAIN_INIT=5.0 GPTQ_ENABLED=1 VAL_LOSS_EVERY=9999 \\\n  torchrun --standalone --nproc_per_node=8 \\\n  records/track_10min_16mb/2026-04-11_GDN_Hybrid_DeltaRule/train_gpt.py\n```\n\nExpected on a cold pod: ~1857\u20131858 steps, quantized BPB ~1.027\u20131.030. See README for full details.\n\n## Compliance\n\nFixed predictor (Track A). No TTT, no RLS, no SLOT, no n-gram mixer at eval time. GPTQ calibration uses model-generated synthetic sequences only. Sliding-window eval is strictly causal, single-pass, normalized softmax distribution.\n\n## Supplemental Evidence\n\nOne warm-cache seed=1337 run (same config, pre-compiled Triton kernels) reached **1.015890 BPB** (2247 steps). This is not part of the submitted 3-seed claim. The official claim is based solely on the cold-cache runs above.",
  "state": "closed",
  "merged": false,
  "labels": [],
  "created_at": "2026-04-11T16:20:56Z",
  "updated_at": "2026-04-11T18:04:45Z",
  "submission_readme": "# Record: GDN-Hybrid \u2014 Gated DeltaNet + Sliding Window Attention\n\n**val_bpb = 1.0283** (3-seed mean, cold cache) | **14.70 MB** | 8\u00d7H100 SXM\n\n*First non-transformer architecture in the 10-min record track.*\n*Beats current SOTA (1.0810) by **5.27 centiBPB** \u2014 largest single improvement in competition history.*\n*No TTT. Fixed predictor. Sliding-window eval only.*\n\n---\n\n## Results\n\n### 3-seed cold-cache runs (VAL_LOSS_EVERY=9999, fresh pods)\n\nAll three seeds run on separate fresh pods. Cold-start signature confirmed: step 1 at ~105s\n(Triton JIT overhead), verifying no prior cache contamination.\n\n| Seed | Steps | EMA BPB  | **Quantized BPB** | Artifact (bytes) |\n|------|-------|----------|-------------------|-----------------|\n| 42   | 1857  | 1.017970 | **1.027163**      | 15,188,240      |\n| 1337 | 1858  | 1.018624 | **1.027614**      | 15,417,768      |\n| 2024 | 1858  | 1.020559 | **1.030148**      | 15,314,099      |\n| **Mean** | \u2014 | **1.019051** | **1.028308**  | \u2014               |\n| **Std**  | \u2014 | **0.001356** | **0.001610**  | \u2014               |\n\nTraining: 590s on 8\u00d7H100 SXM per seed. No in-training validation evals (`VAL_LOSS_EVERY=9999`).\nCold-start overhead (~105s of Triton JIT) accounts for fewer steps (~1858) vs warm cache (~2247).\n\nMerged SOTA (PR #1493): **1.0810 BPB**. 3-seed mean delta: **\u22120.0527 BPB**. Clears the 0.005 threshold.\n\n### Additional Evidence (not part of the submitted claim)\n\nTwo supplemental data points included for completeness. Neither affects the submitted val_bpb.\n\n**Eval-determinism audit \u2014 seed=42 artifact, independent reload:**\n\nThe seed=42 quantized artifact was loaded from disk and re-evaluated independently\nusing `eval_rls.py` (separate process, no training state):\n\n```\nModel loaded from checkpoints/final_model_D_GDN_Hybrid_seed42.int6.ptz\nSliding BPB (stride=64, no XSA): 1.053155\n(Expected from training: 1.053155)\n```\n\nExact match. This confirms the artifact format is self-contained and the sliding-window eval\nis deterministic \u2014 loading and rescoring the artifact yields the same BPB as the training\nlog's roundtrip validation.\n\n**Warm-cache seed=1337 run:**\n\nOne earlier run of seed=1337 was conducted on the same pod after Triton kernels were already\ncompiled (warm cache). With ~52s less JIT overhead, training reached 2247 steps instead of\n1858, producing a lower BPB:\n\n| Seed | Steps | EMA BPB  | Quantized BPB | Artifact (bytes) | Cache |\n|------|-------|----------|---------------|-----------------|-------|\n| 1337 | 2247  | 1.007164 | 1.015890      | 15,802,210      | warm  |\n\nThis is included as a datapoint showing the architecture's capability under favorable\nconditions. It is **not** part of the 3-seed submitted claim and is not reproducible on a\nfresh pod without pre-compiling Triton kernels. The official submission is based solely on\nthe cold-cache runs above.\n\n---\n\n## What This Is\n\nEvery competitive submission since March 18 has been a transformer with incremental improvements:\ndepth recurrence, parallel residuals, SP8192, QK-gain tuning, TTT. This submission replaces the\nentire transformer backbone with **Gated DeltaNet (GDN)** \u2014 a delta-rule linear recurrence model \u2014\nand achieves a new record without any of those stacked tricks.\n\n**The core model** is a Griffin-style hybrid:\n\n```\n[GDN\u00d75] \u2192 [SWA] \u2192 [GDN\u00d75] \u2192 [SWA_shared]\n```\n\n- **GDN layers**: each layer maintains a recurrent key-value associative memory updated by the\n  delta rule. At each token, the memory is queried (read) and updated (write) using learned\n  per-token gates. This is fundamentally different from attention \u2014 there is no O(T\u00b2) computation,\n  no KV cache that grows with sequence length, and the model \"compresses\" past context into a\n  fixed-size hidden state that evolves online.\n- **SWA layers**: two Sliding Window Attention layers (window=512) with shared weights provide\n  local attention. The weight sharing (SWA_shared) reduces parameter count while maintaining\n  expressiveness.\n\nThe result is a model that handles long-range context via its recurrent state and local context\nvia attention, similar in spirit to Griffin/Hawk but using GDN's stronger delta-rule memory update.\n\n---\n\n## Architecture\n\n**Model D \u2014 GDN-Hybrid:**\n- Layout: `[GDN\u00d75] \u2192 [SWA] \u2192 [GDN\u00d75] \u2192 [SWA_shared]` (12 layers total)\n- Dimension: 512, MLP mult: 3\u00d7, GDN head_dim: 64\n- SWA: window=512, 8 heads / 4 KV heads, weight-shared across both SWA layers\n- QK-Gain: 5.0 (learnable per-head scaling, consistent with transformer SOTA finding)\n- BigramHash(3072, 112) + trigram hash embeddings\n- SmearGate on token embeddings\n- Logit softcap at 30.0\n- **Total parameters: 33,862,953**\n\n**GDN implementation:** `fla.layers.GatedDeltaNet` from the Flash Linear Attention library.\nEach layer uses `expand_v=1`, `head_dim=64`, `use_short_conv=True`. The delta rule update:\n```\nh_t = (I - \u03b2_t k_t k_t^T) h_{t-1} + \u03b2_t v_t k_t^T\n```\nwhere \u03b2_t is a learned forgetting gate, k_t/v_t are key/value projections of the current token.\n\n---\n\n## Training\n\n- **Optimizer:** Muon (Newton-Schulz 5) for matrices, AdamW for embeddings/scalars\n- **Steps:** ~1857\u20131858 in 590s (3-seed cold-cache mean, VAL_LOSS_EVERY=9999)\n- **Batch:** 786,432 tokens (384 sequences \u00d7 2048)\n- **LR schedule:** cosine warmup (100 steps) \u2192 constant (no warmdown reached within budget)\n- **EMA:** decay 0.997, applied at end of training\n- **`VAL_LOSS_EVERY=9999`:** In-training validation evals are disabled. Each eval consumes\n  ~141\u2013182s of the 590s budget. With `VAL_LOSS_EVERY=500`, two evals fire at steps 500 and\n  1000, capping training at ~1390 steps. Setting `VAL_LOSS_EVERY=9999` gives the full 590s\n  budget to training. Cold-cache pods reach ~1857\u20131858 steps (105s Triton JIT overhead);\n  warm-cache pods reach ~2247 steps.\n- **`torch._dynamo.config.recompile_limit = 64`:** Defensive guard for FLA's `layer_idx`\n  integer attributes. No longer strictly needed (eval compile was removed) but harmless.\n\n---\n\n## Quantization\n\nFull-Hessian GPTQ with int6 matrices + zstd-22 compression:\n\n1. **Calibration data:** 64 autoregressive sequences \u00d7 2048 tokens, generated from the model\n   itself (AR self-generated, same approach as PR #1019).\n   - RoPE fix: generation starts from `init_len=16` tokens to avoid `T < num_heads`\n     shape mismatch in `apply_rotary_emb` (heads=8, so T\u2208[2,8) causes broadcast failure).\n2. **Hessian collection:** 29 linear layers instrumented; Hessians computed in bfloat16.\n3. **Quantization:** percentile-based clipping search per layer, int6 packing.\n4. **Compression:** zstd level 22.\n5. **Degradation:** ~0.009\u20130.010 BPB across all seeds (EMA\u2192quantized).\n\n---\n\n## Compliance\n\nFixed predictor \u2014 no eval-time adaptation of any kind.\n\nPer Issue #1017 (Track A \u2014 fixed predictor):\n\n- **Condition 1 (Causality):** Sliding-window eval is strictly causal. Each position scored\n  from prefix tokens only. GDN recurrent state is forward-only.\n- **Condition 2 (Normalized distribution):** Standard softmax over full 1024-token vocabulary.\n  No n-gram cache, no logit biasing, no TTT corrections.\n- **Condition 3 (Score before update):** N/A \u2014 no eval-time parameter updates.\n- **Condition 4 (Single pass):** Each validation token scored exactly once. No rescoring.\n\nAdditional:\n- `TTT_ENABLED=0` (no test-time training)\n- No SLOT, no RLS, no n-gram mixer at eval time\n- No pre-quantization adaptation on validation data\n- GPTQ calibration uses model-generated synthetic sequences only (no val data)\n- All 3 artifacts < 16,000,000 bytes \u2713 (14.48\u201314.70 MB)\n- All 3 seeds: training 590s on 8\u00d7H100 SXM \u2713\n\n---\n\n## Reproduction\n\n```bash\n# Install dependencies\npip install sentencepiece zstandard\npip install flash_attn_3 --no-deps  # for SWA layers\npip install flash-linear-attention  # FLA (GDN implementation)\n\n# Download SP1024 dataset\npython3 data/cached_challenge_fineweb.py --variant sp1024\n\n# Train + quantize (590s budget, ~23 min total including GPTQ)\nSEED=1337 ARCH_MODE=D MAX_WALLCLOCK_SECONDS=590 ITERATIONS=9999 \\\n  TRAIN_SEQ_LEN=2048 TRAIN_BATCH_TOKENS=786432 \\\n  QK_GAIN_INIT=5.0 GPTQ_ENABLED=1 VAL_LOSS_EVERY=9999 \\\n  torchrun --standalone --nproc_per_node=8 \\\n  records/track_10min_16mb/2026-04-11_GDN_Hybrid_DeltaRule/train_gpt.py\n```\n\nExpected output on a **cold pod** (fresh Triton cache, as submitted):\n```\n# seed=42\nTraining complete in 590s (1857 steps)\nEMA BPB (no XSA): 1.017970\nQuantized BPB (no XSA): 1.027163\nArtifact: 15,188,240 bytes (14.48 MB)\n\n# seed=1337\nTraining complete in 590s (1858 steps)\nEMA BPB (no XSA): 1.018624\nQuantized BPB (no XSA): 1.027614\nArtifact: 15,417,768 bytes (14.70 MB)\n\n# seed=2024\nTraining complete in 590s (1858 steps)\nEMA BPB (no XSA): 1.020559\nQuantized BPB (no XSA): 1.030148\nArtifact: 15,314,099 bytes (14.60 MB)\n```\n\nCold-start signature: step 1 at ~105s (Triton JIT), step 100 at ~131s.\n\nOn a **warm pod** (pre-compiled Triton cache), expect ~2247 steps and quantized BPB ~1.015\u20131.016.\nThe warm seed=1337 datapoint in Additional Evidence above is the only warm run in this submission.\n\n---\n\n## Key Engineering Notes\n\n### torch.compile recompile_limit\nThe single most impactful engineering fix. FLA's `GatedDeltaNet` stores `layer_idx` as\nan integer `nn.Module` attribute. torch.compile treats this as a static guard, triggering\none full recompilation per unique `layer_idx`. With 10 GDN layers (indices 0\u20139) and the\ndefault `recompile_limit=8`, layers 8 and 9 permanently fall back to eager mode at ~step 500,\nreducing throughput from 3.8 steps/s to ~0.57 steps/s (7\u00d7 slowdown).\n\nFix (line ~55 of train_gpt.py):\n```python\ntorch._dynamo.config.recompile_limit = 64\n```\n\n### GPTQ RoPE shape mismatch\nDuring autoregressive calibration generation, growing sequences from length 1 hits a shape\nmismatch in `apply_rotary_emb`: the function uses `x.shape[-2]` (= `num_heads=8`) to slice\nthe cosine table, so when `T < num_heads`, `cos[:8]` clips to shape `[T, D//2]` which fails\nto broadcast against `[B, T, 8, D//2]` at dimension 2. Fix: start generation with `init_len=16`\ntokens, skipping the problematic `T \u2208 [2, 8)` range.\n\n---\n\n## Attribution\n\nGDN-Hybrid architecture, FLA integration, and GPTQ pipeline originally developed by\n**Christopher-Lee-McClendon** (PR #1370, branch `submission/10L-gdn-puregdn-7k-legal-ttt`).\n\n---\n\n## Included Files\n\n- `README.md` (this file)\n- `submission.json`\n- `train_gpt.py` \u2014 training + quantization script\n- `architectures.py` \u2014 GDN-Hybrid model definition\n- `configs.py` \u2014 Model D configuration\n- `train_seed42.log`\n- `train_seed2024.log`\n- `train_seed1337.log`\n"
}