{
  "number": 1764,
  "title": "Add non-record no-looping SOTA-stack submission scaffold",
  "author": "gmn0105",
  "body": "Adds `records/track_non_record_16mb/2026-04-21_NoLooping_SOTAStack_5Shards_1xH100/` folder with README, submission.json, launcher script, requirements, and 3 seed logs from the 1\u00d7H100 5-shard screen.",
  "state": "open",
  "merged": false,
  "labels": [],
  "created_at": "2026-04-21T15:32:05Z",
  "updated_at": "2026-04-21T15:32:05Z",
  "submission_readme": "# No-looping ablation on the SP8192 SOTA stack (5 shards, 1\u00d7H100 screening) \u2014 Non-record submission\n\nThis folder captures the **\u201cno looping\u201d** ablation used during grant screening: run the current SP8192 SOTA training stack with **layer looping disabled**.\n\n- **Track**: non-record (screening / grant experiments)\n- **Base trainer**: `records/track_10min_16mb/2026-04-09_SP8192_3LayerRecur_ParResid_QK525_LegalTTT/train_gpt.py`\n- **Ablation**: set `NUM_LOOPS=0` (disables depth recurrence / looping)\n- **Budget**: `MAX_WALLCLOCK_SECONDS=600`\n- **Train shards**: 5\n\n## Results (3-seed)\n\nMetric notes:\n- **Pre-quantization post-EMA** isolates model quality before export.\n- **`quantized_sliding_window`** is the post-quant sliding-window BPB reported by this trainer.\n\n| Seed | Steps @ cap | Pre-quant post-EMA `val_bpb` | `quantized_sliding_window val_bpb` | Total submission size (quantized+brotli) |\n|------|-------------|------------------------------:|-----------------------------------:|-----------------------------------------:|\n| 0    | 658         | 1.327667 | 1.317445 | 16,033,831 |\n| 42   | 724         | 1.291048 | 1.280317 | 16,034,416 |\n| 1337 | 724         | 1.289564 | 1.278652 | 16,034,548 |\n| **Mean** | | **1.302760** | **1.292138** | **16,034,265** |\n\n## How to run\n\n```bash\ncd records/track_non_record_16mb/2026-04-21_NoLooping_SOTAStack_5Shards_1xH100\nSEED=1337 RUN_ID=no_looping_1337 MAX_WALLCLOCK_SECONDS=600 NUM_LOOPS=0 \\\n  torchrun --standalone --nproc_per_node=1 train_gpt.py\n```\n\n## Notes\n\n- This submission uses a **thin launcher** that sets the no-looping env var and then executes the base record trainer.\n- Training/eval dependencies should match the base record (FlashAttention 3, etc.).\n\n"
}