{
  "number": 595,
  "title": "Record: Loqui Auris \u2014 10L + SWA + Standard TTT (val_bpb=1.1100)",
  "author": "LoquiAuris",
  "body": "## Summary\n* val_bpb: 1.1100 (seed 1337)\n* 10L d=512, 8 heads, 4 KV heads (GQA), MLP 3x, ReLU\u00b2\n* SWA (29 checkpoints), SmearGate, BigramHash(4096), U-Net skips\n* Standard AdamW TTT: 10 epochs, lr=0.0005\n* Artifact: 15.69 MB (250KB headroom)\n* Platform: 8xH100 SXM, ~5992 steps in 600s\n\n## Acknowledgments\n* Training stack: PR #162 (raahilshah), PR #180 (thwu1)\n* TTT approach: PR #77 (samacqua), PR #442 (sjp611)",
  "state": "closed",
  "merged": false,
  "labels": [],
  "created_at": "2026-03-24T02:56:33Z",
  "updated_at": "2026-03-24T15:55:46Z",
  "submission_readme": "# Record Submission: 10L d=512 SWA + Standard AdamW TTT\n\n**Author:** Loqui Auris ([@LoquiAuris](https://github.com/LoquiAuris))\n**val_bpb:** 1.1100 (seed 1337)\n**Artifact size:** 15,750,007 bytes (15.75 MB)\n**Training time:** ~10 minutes on 8\u00d7H100\n\n## Results\n\n| Seed | Post-quant val_bpb | Post-TTT val_bpb | Artifact (bytes) | Steps |\n|------|-------------------|-----------------|------------------|-------|\n| 1337 | ~1.1510           | **1.1100**      | 15,750,007       | 5,992 |\n\n## Approach\n\n### Architecture\n\nStandard PR #162 transformer stack with the following configuration:\n\n- 10 layers, d_model=512, 8 attention heads, 4 KV heads (GQA)\n- 3\u00d7 FFN expansion (hidden=1536) with ReLU\u00b2 activation\n- SmearGate: learned blend with previous token representation\n- BigramHash: 4096 buckets, dim=128, projected to 512\n- U-Net skip connections between symmetric layer pairs\n- RMSNorm, logit softcap=30.0, orthogonal initialization\n- RoPE positional encoding (persistent=False)\n- Tied embeddings via `F.linear(x, tok_emb.weight)`\n- Vocabulary: sp1024 (1,024 BPE tokens)\n- ~24.7M parameters\n\n### Training\n\n- Optimizer: Muon (matrix_lr=0.02, momentum=0.99 with warmup from 0.92 over 1500 steps) + AdamW for embeddings and scalars\n- Weight decay: 0.04 (Muon), 0.01 (AdamW)\n- Gradient clipping: 0.3\n- Sequence length: 2048\n- Batch size: 786,432 tokens\n- Warmup: 20 steps\n- Warmdown: 3000 iterations (wallclock-based cosine schedule)\n- SWA: start_frac=0.5, checkpoint every 50 steps, **29 checkpoints averaged**\n- Steps completed: ~5,992 in 600s\n\n### Quantization & Compression\n\n- MLP weights: Int5 per-row symmetric (clip=15)\n- Attention weights: Int6 per-row symmetric (clip=31)\n- Embeddings: FP16 passthrough\n- Norms, gates, control tensors: FP16/FP32 passthrough\n- Compression: zstd level 22\n- Artifact: 15.69 MB (250KB headroom)\n\n### Evaluation: Standard AdamW TTT\n\nGlobal fine-tuning on the validation data after training, applied to the quantized-then-dequantized model weights.\n\n**How it works:**\n\nAfter training completes and SWA weights are applied:\n1. Quantize model to Int5/Int6\n2. Save compressed artifact\n3. Load artifact, dequantize back to float\n4. Fine-tune ALL model parameters on validation data using AdamW\n5. Evaluate with sliding window (stride=64, seq_len=2048)\n\n**Key details:**\n- AdamW optimizer (lr=0.0005, no weight decay)\n- 10 epochs over the full validation set\n- Gradient clipping: 1.0\n- Distributed: gradients all-reduced across 8 GPUs\n- TTT improvement: ~0.041 bpb (1.1510 \u2192 1.1100)\n\nStandard TTT modifies the base model weights directly (unlike LoRA TTT which uses ephemeral adapters). The fine-tuned weights are NOT saved \u2014 only the original quantized artifact is the submission. TTT is applied at eval time.\n\n### Comparison: Standard TTT vs LoRA TTT\n\n| Method | Pre-TTT | Post-TTT | Improvement | Time |\n|--------|---------|----------|-------------|------|\n| Standard AdamW TTT | 1.1510 | 1.1100 | -0.041 | ~120s |\n| LoRA TTT (PR #548) | 1.1610 | 1.0865 | -0.074 | ~245s |\n\nLoRA TTT provides a larger improvement (-0.074 vs -0.041) because it adapts per-document rather than globally. Standard TTT is faster but less effective.\n\n## Development Process\n\nThis submission builds on the 1.1508 baseline (PR #350) with the addition of standard AdamW TTT:\n\n1. **Baseline** (PR #350): 1.1508 bpb \u2014 no TTT, SWA only\n2. **+ Standard TTT**: 1.1100 bpb \u2014 AdamW fine-tuning on val data (this submission)\n3. **+ LoRA TTT** (PR #548): 1.0865 bpb \u2014 per-document LoRA adaptation\n\nThe standard TTT approach was implemented based on PR #77 (samacqua) and PR #442 (sjp611). AdamW was chosen over SGD based on published ablations showing -0.019 bpb advantage.\n\n## Hardware & Cost\n\n- Training: 8\u00d7H100 SXM (RunPod)\n- Local testing: Apple Silicon (MPS) for architecture validation\n- Total H100 time: ~30 minutes (single seed)\n- Estimated cost: ~$12 in RunPod credits\n\n## Acknowledgments\n\n- Training stack: PR #162 (raahilshah), PR #180 (thwu1)\n- Standard TTT approach: PR #77 (samacqua), PR #442 (sjp611)\n- SmearGate/BigramHash: @unnir\n- Muon optimizer, SWA, OrthoInit: Parameter Golf community\n\n## Files\n\n- `train_gpt.py` \u2014 Complete training script with environment variable configuration\n- `submission.json` \u2014 Submission metadata\n- `README.md` \u2014 This file\n"
}